klvm/EvalError.py
klvm/KLVMObject.py
klvm/SExp.py
klvm/__init__.py
klvm/as_python.py
klvm/casts.py
klvm/core_ops.py
klvm/costs.py
klvm/more_ops.py
klvm/object_cache.py
klvm/op_utils.py
klvm/operators.py
klvm/py.typed
klvm/read_cache_lookup.py
klvm/run_program.py
klvm/serialize.py
klvm/version.py
klvm-0.9.15.dist-info/licenses/LICENSE
klvm-0.9.15.dist-info/METADATA
klvm-0.9.15.dist-info/WHEEL
klvm-0.9.15.dist-info/top_level.txt
klvm-0.9.15.dist-info/RECORD
