Metadata-Version: 2.4
Name: klvm
Version: 0.9.15
Summary: [Contract Language | Chiklisp] Virtual Machine
Home-page: https://github.com/Chik-Network/klvm
Author: Chik Network, Inc.
Author-email: hello@chiknetwork.com
License: https://opensource.org/licenses/Apache-2.0
Project-URL: Bug Reports, https://github.com/Chik-Network/klvm
Project-URL: Source, https://github.com/Chik-Network/klvm
Classifier: Development Status :: 3 - Alpha
Classifier: Programming Language :: Python :: 3
Classifier: Programming Language :: Python :: 3.8
Classifier: Programming Language :: Python :: 3.9
Classifier: Programming Language :: Python :: 3.10
Classifier: Programming Language :: Python :: 3.11
Classifier: License :: OSI Approved :: Apache Software License
Classifier: Topic :: Security :: Cryptography
Requires-Python: >=3.8.1, <4
License-File: LICENSE
Requires-Dist: chik_rs>=0.2.13
Requires-Dist: importlib_metadata~=8.7
Requires-Dist: typing-extensions~=4.0
Provides-Extra: dev
Requires-Dist: klvm_tools>=0.4.4; extra == "dev"
Requires-Dist: mypy; extra == "dev"
Requires-Dist: pytest; extra == "dev"
Requires-Dist: setuptools; extra == "dev"
Requires-Dist: types-setuptools; extra == "dev"
Dynamic: author
Dynamic: author-email
Dynamic: classifier
Dynamic: description
Dynamic: description-content-type
Dynamic: home-page
Dynamic: license
Dynamic: license-file
Dynamic: project-url
Dynamic: provides-extra
Dynamic: requires-dist
Dynamic: requires-python
Dynamic: summary
